ip_info_all/__init__.py
ip_info_all-0.0.5.dist-info/LICENSE
ip_info_all-0.0.5.dist-info/METADATA
ip_info_all-0.0.5.dist-info/WHEEL
ip_info_all-0.0.5.dist-info/top_level.txt
ip_info_all-0.0.5.dist-info/RECORD
