Metadata-Version: 2.1
Name: ip-info-all
Version: 0.0.5
Summary: get IPV4 or IPV6 info
Home-page: https://github.com/landybird/IPInfo
Author: landybird
Author-email: 1442172978@qq.com
License: UNKNOWN
Platform: UNKNOWN
Classifier: Programming Language :: Python :: 3
Classifier: License :: OSI Approved :: MIT License
Classifier: Operating System :: OS Independent
Requires-Dist: netifaces
